ccautil/__init__.py
ccautil/errors.py
ccautil/util.py
ccautil-0.1.0.dist-info/WHEEL
ccautil-0.1.0.dist-info/METADATA
ccautil-0.1.0.dist-info/RECORD
